Metadata-Version: 1.1
Name: opendank
Version: 0.1
Summary: View images from the WWW in a diashow.
Home-page: https://github.com/lnsp/opendank
Author: the opendank community
Author-email: lennart@mooxmirror.io
License: MIT
Download-URL: https://github.com/lnsp/opendank/tarball/0.1
Keywords: memes,www,diashow
Platform: UNKNOWN
